MANIFEST.in
README.md
pyproject.toml
setup.py
amuse_sphray.egg-info/PKG-INFO
amuse_sphray.egg-info/SOURCES.txt
amuse_sphray.egg-info/dependency_links.txt
amuse_sphray.egg-info/requires.txt
amuse_sphray.egg-info/top_level.txt
src/amuse/community/sphray/Makefile
src/amuse/community/sphray/__init__.py
src/amuse/community/sphray/_version.py
src/amuse/community/sphray/interface.f90
src/amuse/community/sphray/interface.py
src/amuse/community/sphray/data/input/sphray_4K
src/amuse/community/sphray/data/input/test1_sources_001.1
src/amuse/community/sphray/data/input/test2_sources_001.1
src/amuse/community/sphray/data/input/atomic_rates/atomic_rates.txt
src/amuse/community/sphray/data/input/atomic_rates/atomic_rates_Cen.txt
src/amuse/community/sphray/data/input/atomic_rates/atomic_rates_Hui.txt
src/amuse/community/sphray/data/input/atomic_rates/atomic_rates_Hum.txt
src/amuse/community/sphray/data/input/atomic_rates/atomic_rates_Vor.txt
src/amuse/community/sphray/data/input/column_depth/latmon_b2cd_table.txt
src/amuse/community/sphray/data/input/column_depth/tophat_b2cd_table.txt
src/amuse/community/sphray/data/input/spectra/power2.0.cdf
src/amuse/community/sphray/data/input/spectra/power4.0.cdf
src/amuse/community/sphray/data/input/spectra/thermal1e5.cdf
src/amuse/community/sphray/data/input/spectra/thermal6e4.cdf
src/amuse/community/sphray/src/Makefile
src/amuse/community/sphray/src/MakefileTemplate
src/amuse/community/sphray/src/amuse_helpers.F90
src/amuse/community/sphray/src/amuse_mainloop.F90
src/amuse/community/sphray/src/atomic_rates.F90
src/amuse/community/sphray/src/b2cd.F90
src/amuse/community/sphray/src/bdf.F90
src/amuse/community/sphray/src/cen_atomic_rates.F90
src/amuse/community/sphray/src/config.F90
src/amuse/community/sphray/src/cosmology.F90
src/amuse/community/sphray/src/density_test.F90
src/amuse/community/sphray/src/euler.F90
src/amuse/community/sphray/src/gadget_cosmoBH_input.F90
src/amuse/community/sphray/src/gadget_general_class.F90
src/amuse/community/sphray/src/gadget_owls_header_class.F90
src/amuse/community/sphray/src/gadget_owls_input.F90
src/amuse/community/sphray/src/gadget_public_header_class.F90
